banglaspeech2text/__init__.py
banglaspeech2text/cli.py
banglaspeech2text/speech2text.py
banglaspeech2text/utils/__init__.py
banglaspeech2text/utils/converter.py
banglaspeech2text/utils/helpers.py
banglaspeech2text/utils/listed_models.json
banglaspeech2text/utils/loading.py
banglaspeech2text/utils/models.py
banglaspeech2text-1.1.0.dist-info/LICENSE
banglaspeech2text-1.1.0.dist-info/METADATA
banglaspeech2text-1.1.0.dist-info/WHEEL
banglaspeech2text-1.1.0.dist-info/entry_points.txt
banglaspeech2text-1.1.0.dist-info/top_level.txt
banglaspeech2text-1.1.0.dist-info/RECORD
