Metadata-Version: 2.2
Name: BanglaSpeech2Text
Version: 1.1.0
Summary: An open-source offline speech-to-text package for Bangla language.
Home-page: https://github.com/shhossain/BanglaSpeech2Text
Author: shifat (shhossain)
Project-URL: Documentation, https://github.com/shhossain/BanglaSpeech2Text
Project-URL: Source, https://github.com/shhossain/BanglaSpeech2Text
Project-URL: Bug Tracker, https://github.com/shhossain/BanglaSpeech2Text/issues
Keywords: python,speech to text,voice to text,bangla speech to text,bangla speech recognation,whisper model,bangla asr model,offline speech to text,offline bangla speech to text,offline bangla voice recognation,voice recognation
Classifier: Development Status :: 3 - Alpha
Classifier: Intended Audience :: Developers
Classifier: Intended Audience :: Education
Classifier: Intended Audience :: Science/Research
Classifier: License :: OSI Approved :: MIT License
Classifier: Programming Language :: Python :: 3
Classifier: Programming Language :: Python :: 3.6
Classifier: Programming Language :: Python :: 3.7
Classifier: Programming Language :: Python :: 3.8
Classifier: Programming Language :: Python :: 3.9
Classifier: Programming Language :: Python :: 3.10
Classifier: Topic :: Scientific/Engineering :: Artificial Intelligence
Classifier: Topic :: Software Development :: Libraries :: Python Modules
Classifier: Topic :: Text Processing :: Linguistic
Classifier: Topic :: Utilities
Classifier: Operating System :: OS Independent
Requires-Python: >=3.7
License-File: LICENSE
Requires-Dist: transformers
Requires-Dist: faster-whisper
Requires-Dist: torch
Requires-Dist: PyYAML
Requires-Dist: requests
Provides-Extra: dev
Requires-Dist: SpeechRecognition; extra == "dev"
Requires-Dist: pydub; extra == "dev"
Dynamic: author
Dynamic: classifier
Dynamic: description
Dynamic: description-content-type
Dynamic: home-page
Dynamic: keywords
Dynamic: project-url
Dynamic: provides-extra
Dynamic: requires-dist
Dynamic: requires-python
Dynamic: summary
